pingseg/__init__.py
pingseg/seg_gym.py
pingseg/version.py
pingseg-1.0.0a1.dist-info/METADATA
pingseg-1.0.0a1.dist-info/WHEEL
pingseg-1.0.0a1.dist-info/top_level.txt
pingseg-1.0.0a1.dist-info/RECORD
